{"notes_appium_appium-limitations.md":"BJRmyNlA","notes_selenium_index.md":"BR0mZxbh","index.md":"lY_uUWhg","notes_sql_common-sql-data-types.md":"CPxeeZ4x","notes_postman_index.md":"DbquAP5K","notes_appium_appium-image-comparison.md":"D4H2ALOE","notes_postman_dynamic-variables.md":"CYYLIeXs","about_our-story.md":"w7DnYNzr","notes_appium_appium-setup.md":"aEw4-pRE","notes_sql_join.md":"CaXtVMTw","notes_sql_dql.md":"DuNTlnuY","notes_sql_procedures.md":"B38JxCxP","about_index.md":"HTFp4clo","notes_appium_ios_gestures.md":"uyWrcaTK","notes_postman_write-scripts.md":"WL1OB7Qr","notes_appium_ios_touch.md":"DbvItpb2","notes_appium_how-to-swipe-to-element-till-visible.md":"BsDFv0WB","notes_sql_how-to-connect-db.md":"DlQZFxHm","notes_sql_postgresql-commands.md":"n3LBAVe6","notes_appium_index.md":"CsE9R2wP","notes_appium_appium-client-basic-usage.md":"CO-Ydnmh","notes_sql_functions.md":"BBRT_fkv","notes_sql_questions-collections.md":"DrFP-c32","notes_sql_sql-injection.md":"DM3JBqmm","notes_sql_dml.md":"CN-Nn6p4","notes_sql_types-of-sql-commands.md":"C-5YM9-m","notes_sql_ddl.md":"B-1DRctd","notes_sql_index.md":"CW02tq2a","notes_sql_sql-operators.md":"BBPrz5Fb","software_opencv4nodejs-macos.md":"CYdaxpd-","notes_sql_trigger.md":"Bn9y9tnl"}
